pyecceth.cpython-36m-darwin.so
pyecceth-0.1.0.dist-info/METADATA
pyecceth-0.1.0.dist-info/WHEEL
pyecceth-0.1.0.dist-info/top_level.txt
pyecceth-0.1.0.dist-info/RECORD
